album/__init__.py
album/gui/__init__.py
album/gui/actions_list_model.py
album/gui/app.py
album/gui/collection_window.py
album/gui/commandline.py
album/gui/create_shortcut.py
album/gui/solution_util.py
album/gui/solution_window.py
album/gui/worker.py
album/gui/dialog/__init__.py
album/gui/dialog/about_dialog.py
album/gui/dialog/checklist_dialog.py
album/gui/dialog/checklist_table_dialog.py
album/gui/dialog/install_solutions_from_catalog_dialog.py
album/gui/dialog/solution_action_process_thread.py
album/gui/dialog/solutions_action_dialog.py
album/gui/dialog/uninstall_solutions_from_catalog_dialog.py
album/gui/dialog/update_action_item.py
album/gui/dialog/update_album_dialog.py
album/gui/dialog/update_catalog_dialog.py
album/gui/dialog/update_solutions_dialog.py
album/gui/include/pyshortcuts/__init__.py
album/gui/include/pyshortcuts/darwin.py
album/gui/include/pyshortcuts/linux.py
album/gui/include/pyshortcuts/shortcut.py
album/gui/include/pyshortcuts/windows.py
album/gui/include/pyshortcuts/icons/ladder.icns
album/gui/include/pyshortcuts/icons/ladder.ico
album/gui/include/pyshortcuts/icons/ladder.png
album/gui/include/pyshortcuts/icons/py.icns
album/gui/include/pyshortcuts/icons/py.ico
album/gui/resources/__init__.py
album/gui/resources/album-m-200.png
album/gui/resources/album-xs.png
album/gui/resources/album_icon_linux.png
album/gui/resources/album_icon_macos.icns
album/gui/resources/album_icon_windows.ico
album/gui/resources/hi.png
album/gui/update_installation/__init__.py
album/gui/widgets/__init__.py
album/gui/widgets/argument_widget.py
album/gui/widgets/argument_widget_plugins.py
album/gui/widgets/pre_install_solution_widget.py
album/gui/widgets/pre_run_solution_widget.py
album/gui/widgets/solution_status_widget.py
album/gui/widgets/solution_view.py
album/gui/widgets/util.py
album_gui-0.5.0.dist-info/licenses/LICENSE
album_gui-0.5.0.dist-info/METADATA
album_gui-0.5.0.dist-info/WHEEL
album_gui-0.5.0.dist-info/entry_points.txt
album_gui-0.5.0.dist-info/top_level.txt
album_gui-0.5.0.dist-info/RECORD
