Metadata-Version: 2.4
Name: album-gui
Version: 0.5.0
Summary: Plugin for launching the GUI of Album
Home-page: https://gitlab.com/album-app/plugins/album-gui
Author: Kyle Harrington, Jan Philipp Albrecht, Deborah Schmidt
Maintainer: Kyle Harrington, Jan Philipp Albrecht, Deborah Schmidt, Lucas Rieckert, Max Otto
Maintainer-email: album@kyleharrington.com
License: MIT
Project-URL: Source, https://gitlab.com/album-app/plugins/album-gui
Project-URL: Tracker, https://gitlab.com/album-app/plugins/album-gui/issues
Keywords: virtual,environments,imaging,data analysis
Platform: any
Classifier: Development Status :: 3 - Alpha
Classifier: License :: OSI Approved :: MIT License
Classifier: Operating System :: MacOS :: MacOS X
Classifier: Operating System :: Microsoft :: Windows
Classifier: Operating System :: POSIX
Classifier: Programming Language :: Python :: 3.8
Classifier: Programming Language :: Python :: 3.9
Classifier: Programming Language :: Python :: Implementation :: PyPy
Classifier: Topic :: Utilities
Requires-Python: >=3.7
License-File: LICENSE
Requires-Dist: album<0.13,>=0.12
Requires-Dist: PyQt5>=5.15.6
Requires-Dist: pywin32>=303; platform_system == "Windows"
Dynamic: license-file
